{
  "result": {
    "best_iteration": [
      2221,
      2586,
      2156,
      2045,
      2034
    ],
    "score_offline": [
      0.945291,
      0.940543,
      0.947965,
      0.954085,
      0.937454
    ],
    "score_mean_offline": 0.9450676,
    "score_std_offline": 0.005799952537736817,
    "fold_results": [
      {
        "best_iteration": 2221,
        "score_offline": 0.945291,
        "feature_importance_dict": {
          "lda_mean_B_vector_by_15d_5_0": 0.01608383443283321,
          "lda_mean_B_vector_by_15d_5_1": 0.02025804191721642,
          "lda_mean_B_vector_by_15d_5_2": 0.015879502597933328,
          "lda_mean_B_vector_by_15d_5_3": 0.020841847159787496,
          "lda_mean_B_vector_by_15d_5_4": 0.019178002218459923,
          "mean_FTR29_in_global_by_1d_True": 0.025249576741199136,
          "max_ratio_FTR47_in_global_by_1t_False": 0.024578200712242395,
          "std_FTR35_in_global_by_15d_False": 0.021046178994687373,
          "range_FTR9_in_global_by_1d_False": 0.030562204448595948,
          "raw_FTR9_MAX_s_zhang": 0.017893630684803548,
          "max_ratio_FTR43_in_global_by_1t_False": 0.02460739097437095,
          "raw_FTR41_SUM_s_zhang": 0.02551228910035612,
          "raw_FTR33_SUM_s_zhang": 0.020082900344445095,
          "lda_sum_vector_by_1d_False_5_0": 0.022476501838986515,
          "rolling_sum2max_FTR30_30d": 0.02595014303228443,
          "D7_hua_FTR34_SUM_MAX_s_zhang": 0.018740148286531613,
          "mean_FTR48_in_global_by_1t_False": 0.025395528051841906,
          "max_ratio_FTR43_in_global_by_3d_False": 0.021805125810029774,
          "mean_FTR34_in_global_by_1t_False": 0.03275147410823749,
          "D7_hua_FTR0_SUM_MAX_s_zhang": 0.027000992468912372,
          "lda_std_vector_by_1d_False_5_4": 0.01923638274271703,
          "new_FTR36_CONVERT_NUM_NO_ZERO_s_zhang": 0.020520754276373402,
          "rolling_sumratio2max_FTR41_45d": 0.02863564714811139,
          "nunique_ratio2mean_ftr51_by_400d": 0.01885690933504583,
          "std_FTR30_in_global_by_7d_True": 0.022680833673886392,
          "std_FTR48_in_global_by_15d_False": 0.0231186876058147,
          "ftr51_FTR51_B_CONVERT_NUM_UNIQUE_s_zhang": 0.02087103742191605,
          "len_std_count_by_non_zero_group_1d": 0.02028723217934497,
          "mean_FTR9_in_global_by_15d_False": 0.020549944538501955,
          "max_ratio_FTR32_in_global_by_1t_False": 0.01923638274271703,
          "range_FTR36_in_global_by_30d_False": 0.023994395469671317,
          "rolling_sum2max_FTR33_45d": 0.01946990483974546,
          "raw_FTR42_SUM_s_zhang": 0.022534882363243622,
          "max_ratio_FTR42_in_global_by_1t_False": 0.024870103333527935,
          "rolling_sum2max_FTR33_7d": 0.031379531788195456,
          "range_FTR33_in_global_by_30d_True": 0.025103625430556366,
          "rolling_sumratio2max_FTR43_15d": 0.027847510070640433,
          "non_zero_count_FTR33_in_global_by_1d_True": 0.02989082841963921,
          "mean_FTR33_in_global_by_7d_False": 0.024957674119913596,
          "raw_FTR30_MAX_s_zhang": 0.021571603713001344,
          "lda_mean_vector_by_1d_False_5_1": 0.012726954288049507,
          "len_std_count_by_non_zero_group_3d": 0.022330550528343745,
          "sum_std_count_by_non_zero_group_3d": 0.024373868877342518,
          "year_count_max_s_zhang": 0.019061241169945706
        }
      },
      {
        "best_iteration": 2586,
        "score_offline": 0.940543,
        "feature_importance_dict": {
          "lda_mean_B_vector_by_15d_5_0": 0.020539617663036448,
          "lda_mean_B_vector_by_15d_5_1": 0.020436143518638282,
          "lda_mean_B_vector_by_15d_5_2": 0.018884031352665753,
          "lda_mean_B_vector_by_15d_5_3": 0.019970509868846523,
          "lda_mean_B_vector_by_15d_5_4": 0.021858913004113096,
          "mean_FTR29_in_global_by_1d_True": 0.02410947564477326,
          "max_ratio_FTR47_in_global_by_1t_False": 0.025428770985849912,
          "std_FTR35_in_global_by_15d_False": 0.027291305585016943,
          "range_FTR9_in_global_by_1d_False": 0.029360788472980313,
          "raw_FTR9_MAX_s_zhang": 0.01777168430038544,
          "max_ratio_FTR43_in_global_by_1t_False": 0.022686706159298447,
          "raw_FTR41_SUM_s_zhang": 0.019479007682955223,
          "raw_FTR33_SUM_s_zhang": 0.0221693354373076,
          "lda_sum_vector_by_1d_False_5_0": 0.020513749126936907,
          "rolling_sum2max_FTR30_30d": 0.02237628372610394,
          "D7_hua_FTR34_SUM_MAX_s_zhang": 0.024006001500375095,
          "mean_FTR48_in_global_by_1t_False": 0.02467858343896319,
          "max_ratio_FTR43_in_global_by_3d_False": 0.025997878780039837,
          "mean_FTR34_in_global_by_1t_False": 0.03463796983728691,
          "D7_hua_FTR0_SUM_MAX_s_zhang": 0.02421294978917143,
          "lda_std_vector_by_1d_False_5_4": 0.018340792094575366,
          "new_FTR36_CONVERT_NUM_NO_ZERO_s_zhang": 0.01911684817756163,
          "rolling_sumratio2max_FTR41_45d": 0.032025247691233154,
          "nunique_ratio2mean_ftr51_by_400d": 0.01753886747548956,
          "std_FTR30_in_global_by_7d_True": 0.021393279354321337,
          "std_FTR48_in_global_by_15d_False": 0.018314923558475825,
          "ftr51_FTR51_B_CONVERT_NUM_UNIQUE_s_zhang": 0.025506376594148537,
          "len_std_count_by_non_zero_group_1d": 0.01885816281656621,
          "mean_FTR9_in_global_by_15d_False": 0.023566236386682878,
          "max_ratio_FTR32_in_global_by_1t_False": 0.021186331065525,
          "range_FTR36_in_global_by_30d_False": 0.023307551025687455,
          "rolling_sum2max_FTR33_45d": 0.02103111984892775,
          "raw_FTR42_SUM_s_zhang": 0.018677083063869417,
          "max_ratio_FTR42_in_global_by_1t_False": 0.02617895853273663,
          "rolling_sum2max_FTR33_7d": 0.027420648265514654,
          "range_FTR33_in_global_by_30d_True": 0.02470445197506273,
          "rolling_sumratio2max_FTR43_15d": 0.030343792844762914,
          "non_zero_count_FTR33_in_global_by_1d_True": 0.029257314328582147,
          "mean_FTR33_in_global_by_7d_False": 0.022195203973407143,
          "raw_FTR30_MAX_s_zhang": 0.01968595597175156,
          "lda_mean_vector_by_1d_False_5_1": 0.015909149701218407,
          "len_std_count_by_non_zero_group_3d": 0.01849600331117262,
          "sum_std_count_by_non_zero_group_3d": 0.02260910055099982,
          "year_count_max_s_zhang": 0.017926895516982694
        }
      },
      {
        "best_iteration": 2156,
        "score_offline": 0.947965,
        "feature_importance_dict": {
          "lda_mean_B_vector_by_15d_5_0": 0.02404368287679498,
          "lda_mean_B_vector_by_15d_5_1": 0.023742005550862796,
          "lda_mean_B_vector_by_15d_5_2": 0.018522987812236033,
          "lda_mean_B_vector_by_15d_5_3": 0.01960902618559189,
          "lda_mean_B_vector_by_15d_5_4": 0.018070471823337757,
          "mean_FTR29_in_global_by_1d_True": 0.023772173283456016,
          "max_ratio_FTR47_in_global_by_1t_False": 0.029021358754676,
          "std_FTR35_in_global_by_15d_False": 0.02334982502715096,
          "range_FTR9_in_global_by_1d_False": 0.031193435501387715,
          "raw_FTR9_MAX_s_zhang": 0.01924701339447327,
          "max_ratio_FTR43_in_global_by_1t_False": 0.025069385784964402,
          "raw_FTR41_SUM_s_zhang": 0.023530831422710268,
          "raw_FTR33_SUM_s_zhang": 0.019699529383371547,
          "lda_sum_vector_by_1d_False_5_0": 0.016531917461083626,
          "rolling_sum2max_FTR30_30d": 0.019729697115964763,
          "D7_hua_FTR34_SUM_MAX_s_zhang": 0.02310848316640521,
          "mean_FTR48_in_global_by_1t_False": 0.020393387233015568,
          "max_ratio_FTR43_in_global_by_3d_False": 0.02105707735006637,
          "mean_FTR34_in_global_by_1t_False": 0.03131410643176059,
          "D7_hua_FTR0_SUM_MAX_s_zhang": 0.026668275612404972,
          "lda_std_vector_by_1d_False_5_4": 0.017436949438880175,
          "new_FTR36_CONVERT_NUM_NO_ZERO_s_zhang": 0.02033305176782913,
          "rolling_sumratio2max_FTR41_45d": 0.028146494509472667,
          "nunique_ratio2mean_ftr51_by_400d": 0.01894533606854109,
          "std_FTR30_in_global_by_7d_True": 0.02108724508265959,
          "std_FTR48_in_global_by_15d_False": 0.017376613973693736,
          "ftr51_FTR51_B_CONVERT_NUM_UNIQUE_s_zhang": 0.025883914564981295,
          "len_std_count_by_non_zero_group_1d": 0.019428019790032582,
          "mean_FTR9_in_global_by_15d_False": 0.020091709907083383,
          "max_ratio_FTR32_in_global_by_1t_False": 0.025552069506455895,
          "range_FTR36_in_global_by_30d_False": 0.02211294799082901,
          "rolling_sum2max_FTR33_45d": 0.021992277060456138,
          "raw_FTR42_SUM_s_zhang": 0.01927718112706649,
          "max_ratio_FTR42_in_global_by_1t_False": 0.029051526487269216,
          "rolling_sum2max_FTR33_7d": 0.0314951128273199,
          "range_FTR33_in_global_by_30d_True": 0.02546156630867624,
          "rolling_sumratio2max_FTR43_15d": 0.028961023289489563,
          "non_zero_count_FTR33_in_global_by_1d_True": 0.02832750090503198,
          "mean_FTR33_in_global_by_7d_False": 0.019729697115964763,
          "raw_FTR30_MAX_s_zhang": 0.020996741884879933,
          "lda_mean_vector_by_1d_False_5_1": 0.014480511644744782,
          "len_std_count_by_non_zero_group_3d": 0.02190177386267648,
          "sum_std_count_by_non_zero_group_3d": 0.02651743694943888,
          "year_count_max_s_zhang": 0.017738626764812356
        }
      },
      {
        "best_iteration": 2045,
        "score_offline": 0.954085,
        "feature_importance_dict": {
          "lda_mean_B_vector_by_15d_5_0": 0.022857316776235696,
          "lda_mean_B_vector_by_15d_5_1": 0.01667884100316533,
          "lda_mean_B_vector_by_15d_5_2": 0.013939615290966642,
          "lda_mean_B_vector_by_15d_5_3": 0.019144144144144143,
          "lda_mean_B_vector_by_15d_5_4": 0.020848551253956658,
          "mean_FTR29_in_global_by_1d_True": 0.019631117604090576,
          "max_ratio_FTR47_in_global_by_1t_False": 0.028122717311906503,
          "std_FTR35_in_global_by_15d_False": 0.025931336742147554,
          "range_FTR9_in_global_by_1d_False": 0.03564037009982956,
          "raw_FTR9_MAX_s_zhang": 0.023892135378621865,
          "max_ratio_FTR43_in_global_by_1t_False": 0.025840029218407598,
          "raw_FTR41_SUM_s_zhang": 0.022674701728755783,
          "raw_FTR33_SUM_s_zhang": 0.022735573411249085,
          "lda_sum_vector_by_1d_False_5_0": 0.019722425127830533,
          "rolling_sum2max_FTR30_30d": 0.026235695154614075,
          "D7_hua_FTR34_SUM_MAX_s_zhang": 0.022126856586316045,
          "mean_FTR48_in_global_by_1t_False": 0.018991964937910884,
          "max_ratio_FTR43_in_global_by_3d_False": 0.026053080107134162,
          "mean_FTR34_in_global_by_1t_False": 0.03229242756269783,
          "D7_hua_FTR0_SUM_MAX_s_zhang": 0.02194424153883613,
          "lda_std_vector_by_1d_False_5_4": 0.0192354516678841,
          "new_FTR36_CONVERT_NUM_NO_ZERO_s_zhang": 0.018109325541757974,
          "rolling_sumratio2max_FTR41_45d": 0.030648892135378622,
          "nunique_ratio2mean_ftr51_by_400d": 0.018839785731677623,
          "std_FTR30_in_global_by_7d_True": 0.020909422936449963,
          "std_FTR48_in_global_by_15d_False": 0.019600681762843925,
          "ftr51_FTR51_B_CONVERT_NUM_UNIQUE_s_zhang": 0.02133552471390309,
          "len_std_count_by_non_zero_group_1d": 0.020574628682736792,
          "mean_FTR9_in_global_by_15d_False": 0.02154857560262966,
          "max_ratio_FTR32_in_global_by_1t_False": 0.022096420745069394,
          "range_FTR36_in_global_by_30d_False": 0.02587046505965425,
          "rolling_sum2max_FTR33_45d": 0.021700754808862917,
          "raw_FTR42_SUM_s_zhang": 0.023892135378621865,
          "max_ratio_FTR42_in_global_by_1t_False": 0.02218772826880935,
          "rolling_sum2max_FTR33_7d": 0.02946189432675919,
          "range_FTR33_in_global_by_30d_True": 0.022583394205015827,
          "rolling_sumratio2max_FTR43_15d": 0.028731434136839543,
          "non_zero_count_FTR33_in_global_by_1d_True": 0.03000973946919893,
          "mean_FTR33_in_global_by_7d_False": 0.020026783540297053,
          "raw_FTR30_MAX_s_zhang": 0.02014852690528366,
          "lda_mean_vector_by_1d_False_5_1": 0.014000486973459946,
          "len_std_count_by_non_zero_group_3d": 0.019631117604090576,
          "sum_std_count_by_non_zero_group_3d": 0.02483564645726808,
          "year_count_max_s_zhang": 0.018718042366691015
        }
      },
      {
        "best_iteration": 2034,
        "score_offline": 0.937454,
        "feature_importance_dict": {
          "lda_mean_B_vector_by_15d_5_0": 0.018041715665036828,
          "lda_mean_B_vector_by_15d_5_1": 0.016587237729776567,
          "lda_mean_B_vector_by_15d_5_2": 0.016896701120257474,
          "lda_mean_B_vector_by_15d_5_3": 0.019062944853623816,
          "lda_mean_B_vector_by_15d_5_4": 0.01915578387076809,
          "mean_FTR29_in_global_by_1d_True": 0.02082688617936498,
          "max_ratio_FTR47_in_global_by_1t_False": 0.026521012564213655,
          "std_FTR35_in_global_by_15d_False": 0.023643003032741226,
          "range_FTR9_in_global_by_1d_False": 0.026768583276598378,
          "raw_FTR9_MAX_s_zhang": 0.018041715665036828,
          "max_ratio_FTR43_in_global_by_1t_False": 0.029646592808070804,
          "raw_FTR41_SUM_s_zhang": 0.022157578758432876,
          "raw_FTR33_SUM_s_zhang": 0.019867549668874173,
          "lda_sum_vector_by_1d_False_5_0": 0.021724330011759607,
          "rolling_sum2max_FTR30_30d": 0.021043510552701615,
          "D7_hua_FTR34_SUM_MAX_s_zhang": 0.021229188586990157,
          "mean_FTR48_in_global_by_1t_False": 0.02169338367271152,
          "max_ratio_FTR43_in_global_by_3d_False": 0.024633285882280125,
          "mean_FTR34_in_global_by_1t_False": 0.03438138268242867,
          "D7_hua_FTR0_SUM_MAX_s_zhang": 0.0273565637185121,
          "lda_std_vector_by_1d_False_5_4": 0.01924862288791236,
          "new_FTR36_CONVERT_NUM_NO_ZERO_s_zhang": 0.017886983969796374,
          "rolling_sumratio2max_FTR41_45d": 0.0303274122671288,
          "nunique_ratio2mean_ftr51_by_400d": 0.017422788884075013,
          "std_FTR30_in_global_by_7d_True": 0.019186730209816177,
          "std_FTR48_in_global_by_15d_False": 0.019929442346970354,
          "ftr51_FTR51_B_CONVERT_NUM_UNIQUE_s_zhang": 0.02478801757752058,
          "len_std_count_by_non_zero_group_1d": 0.01927956922696045,
          "mean_FTR9_in_global_by_15d_False": 0.02587113944420375,
          "max_ratio_FTR32_in_global_by_1t_False": 0.02683047595469456,
          "range_FTR36_in_global_by_30d_False": 0.02624249551278084,
          "rolling_sum2max_FTR33_45d": 0.020455530110787892,
          "raw_FTR42_SUM_s_zhang": 0.022497988487961876,
          "max_ratio_FTR42_in_global_by_1t_False": 0.02392152008417404,
          "rolling_sum2max_FTR33_7d": 0.02590208578325184,
          "range_FTR33_in_global_by_30d_True": 0.025933032122299932,
          "rolling_sumratio2max_FTR43_15d": 0.03246270966144705,
          "non_zero_count_FTR33_in_global_by_1d_True": 0.02782075880423346,
          "mean_FTR33_in_global_by_7d_False": 0.021043510552701615,
          "raw_FTR30_MAX_s_zhang": 0.02231231045367333,
          "lda_mean_vector_by_1d_False_5_1": 0.01420436962307359,
          "len_std_count_by_non_zero_group_3d": 0.02327164696416414,
          "sum_std_count_by_non_zero_group_3d": 0.02429287615275113,
          "year_count_max_s_zhang": 0.019589032617441358
        }
      }
    ]
  },
  "config": {
    "config_name": "50",
    "note": "gen_stats_value_ftr51",
    "feature_names": [
      "lda_mean_B_vector_by_15d_5_1",
      "lda_mean_B_vector_by_15d_5_3",
      "lda_mean_B_vector_by_15d_5_4",
      "mean_FTR29_in_global_by_1d_True",
      "max_ratio_FTR47_in_global_by_1t_False",
      "std_FTR35_in_global_by_15d_False",
      "range_FTR9_in_global_by_1d_False",
      "raw_FTR9_MAX_s_zhang",
      "max_ratio_FTR43_in_global_by_1t_False",
      "raw_FTR41_SUM_s_zhang",
      "raw_FTR33_SUM_s_zhang",
      "lda_sum_vector_by_1d_False_5_0",
      "rolling_sum2max_FTR30_30d",
      "D7_hua_FTR34_SUM_MAX_s_zhang",
      "mean_FTR48_in_global_by_1t_False",
      "max_ratio_FTR43_in_global_by_3d_False",
      "mean_FTR34_in_global_by_1t_False",
      "D7_hua_FTR0_SUM_MAX_s_zhang",
      "lda_std_vector_by_1d_False_5_4",
      "new_FTR36_CONVERT_NUM_NO_ZERO_s_zhang",
      "rolling_sumratio2max_FTR41_45d",
      "nunique_ratio2mean_ftr51_by_400d",
      "std_FTR30_in_global_by_7d_True",
      "std_FTR48_in_global_by_15d_False",
      "ftr51_FTR51_B_CONVERT_NUM_UNIQUE_s_zhang",
      "len_std_count_by_non_zero_group_1d",
      "mean_FTR9_in_global_by_15d_False",
      "max_ratio_FTR32_in_global_by_1t_False",
      "range_FTR36_in_global_by_30d_False",
      "rolling_sum2max_FTR33_45d",
      "raw_FTR42_SUM_s_zhang",
      "max_ratio_FTR42_in_global_by_1t_False",
      "rolling_sum2max_FTR33_7d",
      "range_FTR33_in_global_by_30d_True",
      "rolling_sumratio2max_FTR43_15d",
      "non_zero_count_FTR33_in_global_by_1d_True",
      "mean_FTR33_in_global_by_7d_False",
      "raw_FTR30_MAX_s_zhang",
      "lda_mean_vector_by_1d_False_5_1",
      "len_std_count_by_non_zero_group_3d",
      "sum_std_count_by_non_zero_group_3d",
      "year_count_max_s_zhang"
    ],
    "model": {
      "name": "Xgboost",
      "model_params": {
        "objective": "binary:logistic",
        "learning_rate": 0.01,
        "eval_metric": "auc",
        "scale_pos_weight": 1,
        "max_depth": 4,
        "gamma": 0,
        "min_child_weight": 1,
        "lambda": 1,
        "alpha": 0,
        "colsample_bytree": 0.7,
        "subsample": 0.9,
        "colsample_bylevel": 0.7,
        "nthread": 20,
        "silent": true,
        "verbose": 0,
        "seed": 2018
      },
      "train_params": {
        "num_boost_round": 60000,
        "early_stopping_rounds": 600
      }
    },
    "cv_params": {
      "shuffle": true,
      "random_state": 100,
      "n_splits": 5
    },
    "save_experiment_result": true,
    "oof": true,
    "ensemble_method": "mean",
    "norm_feat_imp": true
  }
}